LICENSE
README.md
setup.cfg
setup.py
st_login/__init__.py
st_login/utils.py
st_login/widgets.py
st_login.egg-info/PKG-INFO
st_login.egg-info/SOURCES.txt
st_login.egg-info/dependency_links.txt
st_login.egg-info/requires.txt
st_login.egg-info/top_level.txt
st_login.egg-info/zip-safe
tests/__init__.py