Metadata-Version: 2.1
Name: st-login
Version: 0.0.1
Summary: The st_login library is meant for streamlit application developers. It lets you connect your streamlit application to a pre-built and secure Login/ Sign-Up page
Home-page: https://github.com/lijiacaigit/st_login
Author: Lijiacai
Author-email: 1050518702@qq.com
License: UNKNOWN
Platform: UNKNOWN
Classifier: Programming Language :: Python :: 3
Classifier: License :: OSI Approved :: MIT License
Classifier: Operating System :: OS Independent
Requires-Python: >=3.7.1
License-File: LICENSE
